Metadata-Version: 2.1
Name: getnamesprzemek
Version: 1.0.0
Summary: Generate random names with lenght
Home-page: https://github.com/treyhunner/names
Author: Przemek Dmowski
Author-email: przemek_dei@op.pl
License: UNKNOWN
Keywords: random names
Platform: UNKNOWN
